fujielab/asr_parallel_cbs/__init__.py
fujielab/asr_parallel_cbs/espnet_ext/espnet/nets/beam_search_parallel_transducer_online.py
fujielab/asr_parallel_cbs/espnet_ext/espnet/nets/pytorch_backend/transformer/attention.py
fujielab/asr_parallel_cbs/espnet_ext/espnet2/asr/encoder/contextual_block_parallel_conformer_encoder.py
fujielab/asr_parallel_cbs/espnet_ext/espnet2/asr/transducer/transducer_decoder.py
fujielab/asr_parallel_cbs/espnet_ext/espnet2/asr_transducer/joint_network.py
fujielab/asr_parallel_cbs/espnet_ext/espnet2/bin/asr_parallel_transducer_inference.py
fujielab/asr_parallel_cbs/espnet_ext/espnet2/tasks/asr.py
fujielab_asr_parallel_cbs-0.1.1.dist-info/licenses/LICENSE
tests/test_beamsearch.py
tests/test_jointnetwork.py
tests/test_rnntloss.py
tests/test_transducer_decoder.py
warprnnt_pytorch/__init__.py
warprnnt_pytorch/warprnnt_pytorch.py
fujielab_asr_parallel_cbs-0.1.1.dist-info/METADATA
fujielab_asr_parallel_cbs-0.1.1.dist-info/WHEEL
fujielab_asr_parallel_cbs-0.1.1.dist-info/top_level.txt
fujielab_asr_parallel_cbs-0.1.1.dist-info/RECORD
