Metadata-Version: 2.4
Name: fujielab-asr-parallel-cbs
Version: 0.1.1
Summary: Parallel CBS Transformer Based ASR
Author-email: Shinya Fujie <shinya.fujie@p.chibakoudai.jp>
License:                                  Apache License
Project-URL: Homepage, https://github.com/fujielab/fujielab-asr-parallel-cbs
Requires-Python: <3.12,>=3.11
License-File: LICENSE
Requires-Dist: espnet==202301
Requires-Dist: espnet_model_zoo
Requires-Dist: torchaudio
Requires-Dist: typeguard==2.13.3
Dynamic: license-file
